{"created":1598535589,"d1":"ia600707.us.archive.org","d2":"ia800707.us.archive.org","dir":"/29/items/homo033","files":[{"name":"Asher - Distances.afpk","source":"derivative","format":"Columbia Peaks","original":"Asher - Distances.mp3","mtime":"1544486339","size":"852720","md5":"6b98dac233058c6bbbb98c5d8b60368f","crc32":"00912b0f","sha1":"e49b1107530998d8984fa005cfead8a6838bca7f"},{"name":"Asher - Distances.mp3","source":"original","mtime":"1544486118","size":"79239168","md5":"43ffd555b70d222a5cff7cf754e09b35","crc32":"30d398bb","sha1":"5f040b7a4609ef179a9c25efd0e692732892ca97","format":"VBR MP3","length":"1980.43","height":"348","width":"535","title":"Distances","artist":"Asher","album":"Distances","track":"1\/1","genre":"Electronic","external-identifier":"urn:acoustid:9a14c069-592d-48ad-a832-1b2bf9dfc5ac","external-identifier-match-date":"acoustid:2019-03-29T06:45:59Z"},{"name":"Asher - Distances.ogg","source":"derivative","format":"Ogg Vorbis","original":"Asher - Distances.mp3","mtime":"1544486215","size":"18153261","md5":"5549bd2a78c6441a52218a227ec47600","crc32":"0af60d07","sha1":"47fe43b097b674348f41de1900cba85b510f667a","length":"1980.38","height":"0","width":"0"},{"name":"Asher - Distances.png","source":"derivative","format":"PNG","original":"Asher - Distances.mp3","mtime":"1544486295","size":"11428","md5":"02345fc97b4a523e7136ea6ba825a02c","crc32":"3ab0ee07","sha1":"43186b11d8ef4aa3d78e3dfd1ac59798d5c3211b"},{"name":"Asher - Distances_spectrogram.png","source":"derivative","format":"Spectrogram","original":"Asher - Distances.mp3","mtime":"1544486310","size":"191999","md5":"bfaf57d5a8b89fe6d5cc668cd208b98f","crc32":"7f790092","sha1":"d52ac08fb747e7358ed08d06bd5bc0fa678d5826"},{"name":"__ia_thumb.jpg","source":"original","mtime":"1544486343","size":"2745","md5":"18c20049725520e090ef76bd0b3a45d5","crc32":"6f402ddb","sha1":"4703d50603a53cfa3a738072a11ad05608aa8233","format":"Item Tile","rotation":"0"},{"name":"homo033_archive.torrent","source":"metadata","btih":"914dcd4e7d6db9ccdb89c9f15aebd2e94cce6e50","mtime":"1596318283","size":"6206","md5":"b208e663de9c3cc5bd34901f2179d605","crc32":"20b985ae","sha1":"9ed74927c636c2b49c74ac8ed42ba74c389d47a6","format":"Archive BitTorrent"},{"name":"homo033_files.xml","source":"original","format":"Metadata","md5":"0d3942e870d2bcf71c14598aec2d874e"},{"name":"homo033_meta.sqlite","source":"original","mtime":"1544486143","size":"9216","md5":"5541b625d2a4890ceae1d1ebbdcf56c5","crc32":"8717c234","sha1":"d2660b5e1837bbaca4bc2eaa4e3241848198d46e","format":"Metadata"},{"name":"homo033_meta.xml","source":"original","mtime":"1596318281","size":"838","format":"Metadata","md5":"f7adb96cf4b30fcef980f6f87d9f7ebb","crc32":"4ba32464","sha1":"cd874fa269024ca3f58865b015862a5a118b3da6"}],"files_count":10,"item_last_updated":1596318283,"item_size":98467581,"metadata":{"identifier":"homo033","mediatype":"audio","collection":"opensource_audio","creator":"Asher","date":"2009","description":"Distances","licenseurl":"http://creativecommons.org/licenses/by/4.0/","scanner":"Internet Archive HTML5 Uploader 1.6.3","subject":"Abstract","title":"Distances","publicdate":"2018-12-10 23:55:19","uploader":"davidkirby@homophoni.com","addeddate":"2018-12-10 23:55:19","curation":"[curator]validator@archive.org[/curator][date]20181210235555[/date][comment]checked for malware[/comment]","external_metadata_update":"2019-03-29T06:45:59Z","backup_location":"ia906805_7"},"server":"ia800707.us.archive.org","uniq":548687037,"workable_servers":["ia800707.us.archive.org","ia600707.us.archive.org"]}